songlink/__init__.py
songlink-1a1.post1.dist-info/LICENSE
songlink-1a1.post1.dist-info/METADATA
songlink-1a1.post1.dist-info/WHEEL
songlink-1a1.post1.dist-info/RECORD
