Metadata-Version: 2.3
Name: songlink
Version: 1a1.post1
Summary: An unofficial lightweight, type hinted library that helps query the songlink api: https://odesli.co/
License: MIT
Author: Flinty
Author-email: blobjo7@gmail.com
Requires-Python: >=3.9
Classifier: License :: OSI Approved :: MIT License
Classifier: Programming Language :: Python :: 3
Classifier: Programming Language :: Python :: 3.9
Classifier: Programming Language :: Python :: 3.10
Classifier: Programming Language :: Python :: 3.11
Classifier: Programming Language :: Python :: 3.12
Classifier: Programming Language :: Python :: 3.13
